pk3make/__init__.py
pk3make/__main__.py
pk3make/modules/doomglob.py
pk3make/modules/doompic.py
pk3make/modules/pk3makefile.py
pk3make/modules/pk3zip.py
pk3make-2026.1.0.dist-info/METADATA
pk3make-2026.1.0.dist-info/WHEEL
pk3make-2026.1.0.dist-info/entry_points.txt
pk3make-2026.1.0.dist-info/licenses/LICENSE
pk3make-2026.1.0.dist-info/RECORD
