Metadata-Version: 2.4
Name: pk3make
Version: 2026.1.0
Summary: Build system for Weissblatt PK3 files
Project-URL: Homepage, https://github.com/liquidunderground/pk3make
Project-URL: GitHub, https://github.com/liquidunderground/pk3make
Project-URL: Issues, https://github.com/liquidunderground/pk3make/issues
Author-email: Zibon Badi <zibonbadi@gmail.com>
License-Expression: LGPL-3.0-or-later
License-File: LICENSE
Classifier: Environment :: Console
Classifier: License :: OSI Approved :: GNU Lesser General Public License v3 or later (LGPLv3+)
Classifier: Operating System :: OS Independent
Classifier: Programming Language :: Python :: 3
Classifier: Topic :: Software Development :: Build Tools
Requires-Python: >=3.14
Requires-Dist: colormath2
Requires-Dist: natsort
Requires-Dist: pillow
